rapid_paraformer/__init__.py
rapid_paraformer/main.py
rapid_paraformer/utils.py
rapid_paraformer/kaldifeat/LICENSE
rapid_paraformer/kaldifeat/README.md
rapid_paraformer/kaldifeat/__init__.py
rapid_paraformer/kaldifeat/feature.py
rapid_paraformer/kaldifeat/ivector.py
rapid_paraformer-2.0.5.dist-info/METADATA
rapid_paraformer-2.0.5.dist-info/WHEEL
rapid_paraformer-2.0.5.dist-info/entry_points.txt
rapid_paraformer-2.0.5.dist-info/top_level.txt
rapid_paraformer-2.0.5.dist-info/RECORD
